{
  "years": {
    "2022": {
      "countries": [
        {
          "country": "India",
          "ageGroups": {
            "18-24": 2234,
            "25-34": 12394,
            "35-44": 12953,
            "45-54": 10473,
            "55-64": 1073,
            "65+": 873
          },
          "total": 40000
        }
      ]
    },
    "2023": {
      "countries": [
        {
          "country": "India",
          "ageGroups": {
            "18-24": 30335,
            "25-34": 106954,
            "35-44": 69402,
            "45-54": 60316,
            "55-64": 33363,
            "65+": 2474
          },
          "total": 302844
        },
        {
          "country": "UK",
          "ageGroups": {
            "18-24": 21204,
            "25-34": 51905,
            "35-44": 13919,
            "45-54": 15741,
            "55-64": 15871,
            "65+": 11448
          },
          "total": 130088
        },
        {
          "country": "USA",
          "ageGroups": {
            "18-24": 6117,
            "25-34": 15757,
            "35-44": 6998,
            "45-54": 7137,
            "55-64": 8203,
            "65+": 2132
          },
          "total": 46344
        },
        {
          "country": "Germany",
          "ageGroups": {
            "18-24": 29019,
            "25-34": 45834,
            "35-44": 8716,
            "45-54": 8511,
            "55-64": 7896,
            "65+": 2563
          },
          "total": 102539
        },
        {
          "country": "China",
          "ageGroups": {
            "18-24": 13287,
            "25-34": 31998,
            "35-44": 18585,
            "45-54": 3520,
            "55-64": 1112,
            "65+": 287
          },
          "total": 68789
        },
        {
          "country": "France",
          "ageGroups": {
            "18-24": 10406,
            "25-34": 21657,
            "35-44": 7538,
            "45-54": 7031,
            "55-64": 7706,
            "65+": 1913
          },
          "total": 56251
        },
        {
          "country": "Australia",
          "ageGroups": {
            "18-24": 18568,
            "25-34": 14859,
            "35-44": 8991,
            "45-54": 7440,
            "55-64": 11149,
            "65+": 6429
          },
          "total": 67436
        },
        {
          "country": "Japan",
          "ageGroups": {
            "18-24": 6756,
            "25-34": 8812,
            "35-44": 1488,
            "45-54": 608,
            "55-64": 901,
            "65+": 1018
          },
          "total": 19583
        },
        {
          "country": "Canada",
          "ageGroups": {
            "18-24": 6371,
            "25-34": 14765,
            "35-44": 12920,
            "45-54": 4307,
            "55-64": 3472,
            "65+": 2109
          },
          "total": 43944
        },
        {
          "country": "Singapore",
          "ageGroups": {
            "18-24": 1386,
            "25-34": 3717,
            "35-44": 1129,
            "45-54": 1224,
            "55-64": 1444,
            "65+": 651
          },
          "total": 9551
        },
        {
          "country": "Italy",
          "ageGroups": {
            "18-24": 3315,
            "25-34": 10520,
            "35-44": 5360,
            "45-54": 1068,
            "55-64": 1868,
            "65+": 111
          },
          "total": 22242
        },
        {
          "country": "Bangladesh",
          "ageGroups": {
            "18-24": 2858,
            "25-34": 8926,
            "35-44": 3019,
            "45-54": 1770,
            "55-64": 1270,
            "65+": 3
          },
          "total": 17846
        },
        {
          "country": "South Korea",
          "ageGroups": {
            "18-24": 811,
            "25-34": 3562,
            "35-44": 1753,
            "45-54": 972,
            "55-64": 198,
            "65+": 2
          },
          "total": 7298
        },
        {
          "country": "Russia",
          "ageGroups": {
            "18-24": 38315,
            "25-34": 112376,
            "35-44": 32785,
            "45-54": 10270,
            "55-64": 3752,
            "65+": 0
          },
          "total": 197498
        },
        {
          "country": "Malaysia",
          "ageGroups": {
            "18-24": 810,
            "25-34": 6466,
            "35-44": 2090,
            "45-54": 962,
            "55-64": 361,
            "65+": 251
          },
          "total": 10940
        }
      ]
    },
    "2024": {
      "countries": [
        {
          "country": "India",
          "ageGroups": {
            "18-24": 26686,
            "25-34": 165122,
            "35-44": 106745,
            "45-54": 80893,
            "55-64": 22934,
            "65+": 14594
          },
          "total": 416974
        },
        {
          "country": "UK",
          "ageGroups": {
            "18-24": 43009,
            "25-34": 60309,
            "35-44": 34627,
            "45-54": 15188,
            "55-64": 13762,
            "65+": 11444
          },
          "total": 178339
        },
        {
          "country": "USA",
          "ageGroups": {
            "18-24": 12809,
            "25-34": 18822,
            "35-44": 9416,
            "45-54": 8821,
            "55-64": 3939,
            "65+": 5725
          },
          "total": 59532
        },
        {
          "country": "Germany",
          "ageGroups": {
            "18-24": 37559,
            "25-34": 63279,
            "35-44": 17691,
            "45-54": 8437,
            "55-64": 4627,
            "65+": 4491
          },
          "total": 136084
        },
        {
          "country": "China",
          "ageGroups": {
            "18-24": 15165,
            "25-34": 59805,
            "35-44": 37419,
            "45-54": 12401,
            "55-64": 812,
            "65+": 6079
          },
          "total": 131681
        },
        {
          "country": "France",
          "ageGroups": {
            "18-24": 15802,
            "25-34": 38262,
            "35-44": 19175,
            "45-54": 8611,
            "55-64": 3729,
            "65+": 3196
          },
          "total": 88775
        },
        {
          "country": "Australia",
          "ageGroups": {
            "18-24": 11644,
            "25-34": 33411,
            "35-44": 8868,
            "45-54": 8778,
            "55-64": 17646,
            "65+": 9226
          },
          "total": 89573
        },
        {
          "country": "Japan",
          "ageGroups": {
            "18-24": 8764,
            "25-34": 13936,
            "35-44": 4503,
            "45-54": 1157,
            "55-64": 1734,
            "65+": 335
          },
          "total": 30429
        },
        {
          "country": "Canada",
          "ageGroups": {
            "18-24": 4946,
            "25-34": 13388,
            "35-44": 9378,
            "45-54": 3131,
            "55-64": 8660,
            "65+": 2709
          },
          "total": 42212
        },
        {
          "country": "Singapore",
          "ageGroups": {
            "18-24": 2153,
            "25-34": 5225,
            "35-44": 1045,
            "45-54": 1146,
            "55-64": 2078,
            "65+": 944
          },
          "total": 12591
        },
        {
          "country": "Italy",
          "ageGroups": {
            "18-24": 5270,
            "25-34": 20484,
            "35-44": 8328,
            "45-54": 2794,
            "55-64": 1826,
            "65+": 7
          },
          "total": 38709
        },
        {
          "country": "Bangladesh",
          "ageGroups": {
            "18-24": 3244,
            "25-34": 20530,
            "35-44": 7515,
            "45-54": 6724,
            "55-64": 1384,
            "65+": 158
          },
          "total": 39555
        },
        {
          "country": "South Korea",
          "ageGroups": {
            "18-24": 1080,
            "25-34": 4655,
            "35-44": 2300,
            "45-54": 1750,
            "55-64": 1015,
            "65+": 0
          },
          "total": 10800
        },
        {
          "country": "Russia",
          "ageGroups": {
            "18-24": 42605,
            "25-34": 97931,
            "35-44": 49067,
            "45-54": 9894,
            "55-64": 2423,
            "65+": 0
          },
          "total": 201920
        },
        {
          "country": "Malaysia",
          "ageGroups": {
            "18-24": 1955,
            "25-34": 9078,
            "35-44": 2584,
            "45-54": 2125,
            "55-64": 1071,
            "65+": 187
          },
          "total": 17000
        },
        {
          "country": "Spain",
          "ageGroups": {
            "18-24": 3300,
            "25-34": 18812,
            "35-44": 10316,
            "45-54": 5500,
            "55-64": 0,
            "65+": 0
          },
          "total": 37928
        },
        {
          "country": "Switzerland",
          "ageGroups": {
            "18-24": 4653,
            "25-34": 16585,
            "35-44": 3401,
            "45-54": 2148,
            "55-64": 1700,
            "65+": 1342
          },
          "total": 29829
        }
      ]
    },
    "2019": {
      "countries": [
        {
          "country": "India",
          "ageGroups": {
            "18-24": 32305,
            "25-34": 138096,
            "35-44": 93721,
            "45-54": 70290,
            "55-64": 10650,
            "65+": 9940
          },
          "total": 355002
        },
        {
          "country": "UK",
          "ageGroups": {
            "18-24": 52112,
            "25-34": 83320,
            "35-44": 16333,
            "45-54": 19712,
            "55-64": 12755,
            "65+": 14544
          },
          "total": 198776
        },
        {
          "country": "USA",
          "ageGroups": {
            "18-24": 5426,
            "25-34": 37227,
            "35-44": 9350,
            "45-54": 7147,
            "55-64": 3705,
            "65+": 5977
          },
          "total": 68832
        },
        {
          "country": "Germany",
          "ageGroups": {
            "18-24": 33320,
            "25-34": 76083,
            "35-44": 12411,
            "45-54": 5666,
            "55-64": 3777,
            "65+": 3642
          },
          "total": 134899
        },
        {
          "country": "China",
          "ageGroups": {
            "18-24": 50695,
            "25-34": 65802,
            "35-44": 40454,
            "45-54": 7554,
            "55-64": 3022,
            "65+": 336
          },
          "total": 167863
        },
        {
          "country": "France",
          "ageGroups": {
            "18-24": 17086,
            "25-34": 48631,
            "35-44": 7448,
            "45-54": 6922,
            "55-64": 6835,
            "65+": 701
          },
          "total": 87623
        },
        {
          "country": "Australia",
          "ageGroups": {
            "18-24": 11661,
            "25-34": 35108,
            "35-44": 13793,
            "45-54": 9993,
            "55-64": 14071,
            "65+": 8048
          },
          "total": 92674
        },
        {
          "country": "Japan",
          "ageGroups": {
            "18-24": 8006,
            "25-34": 14293,
            "35-44": 5179,
            "45-54": 817,
            "55-64": 667,
            "65+": 1117
          },
          "total": 30079
        },
        {
          "country": "Canada",
          "ageGroups": {
            "18-24": 6676,
            "25-34": 19297,
            "35-44": 6822,
            "45-54": 3606,
            "55-64": 6773,
            "65+": 5555
          },
          "total": 48729
        },
        {
          "country": "Singapore",
          "ageGroups": {
            "18-24": 3065,
            "25-34": 5548,
            "35-44": 1290,
            "45-54": 1291,
            "55-64": 2330,
            "65+": 347
          },
          "total": 13871
        },
        {
          "country": "Italy",
          "ageGroups": {
            "18-24": 6368,
            "25-34": 15730,
            "35-44": 7416,
            "45-54": 3404,
            "55-64": 3078,
            "65+": 151
          },
          "total": 36147
        },
        {
          "country": "Bangladesh",
          "ageGroups": {
            "18-24": 1090,
            "25-34": 4378,
            "35-44": 1751,
            "45-54": 893,
            "55-64": 140,
            "65+": 9
          },
          "total": 8261
        },
        {
          "country": "South Korea",
          "ageGroups": {
            "18-24": 2304,
            "25-34": 7686,
            "35-44": 5418,
            "45-54": 1962,
            "55-64": 630,
            "65+": 0
          },
          "total": 18000
        },
        {
          "country": "Russia",
          "ageGroups": {
            "18-24": 16285,
            "25-34": 47790,
            "35-44": 19661,
            "45-54": 1572,
            "55-64": 1226,
            "65+": 15
          },
          "total": 86549
        },
        {
          "country": "Malaysia",
          "ageGroups": {
            "18-24": 3016,
            "25-34": 8765,
            "35-44": 2627,
            "45-54": 1599,
            "55-64": 435,
            "65+": 419
          },
          "total": 16861
        }
      ]
    }
  }
}